{
  "indexes": [
    {
      "collectionGroup": "gymPresence",
      "queryScope": "COLLECTION",
      "fields": [
        { "fieldPath": "gymId", "order": "ASCENDING" },
        { "fieldPath": "isActive", "order": "ASCENDING" },
        { "fieldPath": "checkedInAt", "order": "DESCENDING" }
      ]
    },
    {
      "collectionGroup": "gymPresence",
      "queryScope": "COLLECTION",
      "fields": [
        { "fieldPath": "gymId", "order": "ASCENDING" },
        { "fieldPath": "userRole", "order": "ASCENDING" },
        { "fieldPath": "checkedInAt", "order": "DESCENDING" }
      ]
    },
    {
      "collectionGroup": "gymPresence",
      "queryScope": "COLLECTION",
      "fields": [
        { "fieldPath": "gymId", "order": "ASCENDING" },
        { "fieldPath": "isActive", "order": "ASCENDING" },
        { "fieldPath": "userRole", "order": "ASCENDING" },
        { "fieldPath": "checkedInAt", "order": "DESCENDING" }
      ]
    },
    {
      "collectionGroup": "gymPresence",
      "queryScope": "COLLECTION",
      "fields": [
        { "fieldPath": "gymId", "order": "ASCENDING" },
        { "fieldPath": "userId", "order": "ASCENDING" },
        { "fieldPath": "isActive", "order": "ASCENDING" }
      ]
    },
    {
      "collectionGroup": "appointments",
      "queryScope": "COLLECTION",
      "fields": [
        { "fieldPath": "subscriptionId", "order": "ASCENDING" },
        { "fieldPath": "status", "order": "ASCENDING" }
      ]
    },
    {
      "collectionGroup": "subscriptions",
      "queryScope": "COLLECTION",
      "fields": [
        { "fieldPath": "studentId", "order": "ASCENDING" },
        { "fieldPath": "status", "order": "ASCENDING" }
      ]
    },
    {
      "collectionGroup": "appointments",
      "queryScope": "COLLECTION",
      "fields": [
        { "fieldPath": "subscriptionId", "order": "ASCENDING" },
        { "fieldPath": "sessionNumber", "order": "ASCENDING" }
      ]
    },
    {
      "collectionGroup": "activityLogs",
      "queryScope": "COLLECTION",
      "fields": [
        { "fieldPath": "gymId", "order": "ASCENDING" },
        { "fieldPath": "timestamp", "order": "DESCENDING" }
      ]
    },
    {
      "collectionGroup": "activityLogs",
      "queryScope": "COLLECTION",
      "fields": [
        { "fieldPath": "gymId", "order": "ASCENDING" },
        { "fieldPath": "category", "order": "ASCENDING" },
        { "fieldPath": "timestamp", "order": "DESCENDING" }
      ]
    },
    {
      "collectionGroup": "activityLogs",
      "queryScope": "COLLECTION",
      "fields": [
        { "fieldPath": "gymId", "order": "ASCENDING" },
        { "fieldPath": "action", "order": "ASCENDING" },
        { "fieldPath": "timestamp", "order": "DESCENDING" }
      ]
    },
    {
      "collectionGroup": "activityLogs",
      "queryScope": "COLLECTION",
      "fields": [
        { "fieldPath": "gymId", "order": "ASCENDING" },
        { "fieldPath": "category", "order": "ASCENDING" },
        { "fieldPath": "action", "order": "ASCENDING" },
        { "fieldPath": "timestamp", "order": "DESCENDING" }
      ]
    },
    {
      "collectionGroup": "workoutSchedules",
      "queryScope": "COLLECTION",
      "fields": [
        { "fieldPath": "coachId", "order": "ASCENDING" },
        { "fieldPath": "isActive", "order": "ASCENDING" }
      ]
    },
    {
      "collectionGroup": "appointments",
      "queryScope": "COLLECTION",
      "fields": [
        { "fieldPath": "coachId", "order": "ASCENDING" },
        { "fieldPath": "date", "order": "ASCENDING" }
      ]
    },
    {
      "collectionGroup": "notifications",
      "queryScope": "COLLECTION",
      "fields": [
        { "fieldPath": "gymId", "order": "ASCENDING" },
        { "fieldPath": "createdAt", "order": "DESCENDING" }
      ]
    },
    {
      "collectionGroup": "notifications",
      "queryScope": "COLLECTION",
      "fields": [
        { "fieldPath": "gymId", "order": "ASCENDING" },
        { "fieldPath": "isRead", "order": "ASCENDING" }
      ]
    },
    {
      "collectionGroup": "subscriptions",
      "queryScope": "COLLECTION",
      "fields": [
        { "fieldPath": "type", "order": "ASCENDING" },
        { "fieldPath": "status", "order": "ASCENDING" },
        { "fieldPath": "isCommitmentActive", "order": "ASCENDING" },
        { "fieldPath": "commitmentEndsAt", "order": "ASCENDING" }
      ]
    },
    {
      "collectionGroup": "paymentRequests",
      "queryScope": "COLLECTION",
      "fields": [
        { "fieldPath": "gymId", "order": "ASCENDING" },
        { "fieldPath": "createdAt", "order": "DESCENDING" }
      ]
    },
    {
      "collectionGroup": "paymentRequests",
      "queryScope": "COLLECTION",
      "fields": [
        { "fieldPath": "gymId", "order": "ASCENDING" },
        { "fieldPath": "status", "order": "ASCENDING" },
        { "fieldPath": "createdAt", "order": "DESCENDING" }
      ]
    },
    {
      "collectionGroup": "paymentRequests",
      "queryScope": "COLLECTION",
      "fields": [
        { "fieldPath": "status", "order": "ASCENDING" },
        { "fieldPath": "createdAt", "order": "DESCENDING" }
      ]
    },
    {
      "collectionGroup": "measurements",
      "queryScope": "COLLECTION",
      "fields": [
        { "fieldPath": "studentId", "order": "ASCENDING" },
        { "fieldPath": "measurementDate", "order": "DESCENDING" }
      ]
    },
    {
      "collectionGroup": "subscriptions",
      "queryScope": "COLLECTION",
      "fields": [
        { "fieldPath": "type", "order": "ASCENDING" },
        { "fieldPath": "status", "order": "ASCENDING" }
      ]
    },
    {
      "collectionGroup": "parqTests",
      "queryScope": "COLLECTION",
      "fields": [
        { "fieldPath": "studentId", "order": "ASCENDING" },
        { "fieldPath": "testDate", "order": "DESCENDING" }
      ]
    },
    {
      "collectionGroup": "workoutSchedules",
      "queryScope": "COLLECTION",
      "fields": [
        { "fieldPath": "studentId", "order": "ASCENDING" },
        { "fieldPath": "isActive", "order": "ASCENDING" }
      ]
    }
  ],
  "fieldOverrides": []
}
